link/__init__.py
link/model/__init__.py
link/model/feature.py
link.model-0.10.dist-info/DESCRIPTION.rst
link.model-0.10.dist-info/METADATA
link.model-0.10.dist-info/RECORD
link.model-0.10.dist-info/WHEEL
link.model-0.10.dist-info/metadata.json
link.model-0.10.dist-info/top_level.txt
