Metadata-Version: 2.0
Name: link.model
Version: 0.10
Summary: Provides a Model factory based on data schema for middlewares
Home-page: https://github.com/linkdd/link.model
Author: David Delassus
Author-email: david.jose.delassus@gmail.com
License: MIT
Keywords: link model schema
Platform: UNKNOWN
Classifier: Development Status :: 4 - Beta
Classifier: License :: OSI Approved :: MIT License
Classifier: Operating System :: OS Independent
Classifier: Topic :: Utilities
Classifier: Topic :: Software Development :: Libraries :: Python Modules
Classifier: Intended Audience :: Developers
Classifier: Programming Language :: Python
Classifier: Programming Language :: Python :: 2.7
Classifier: Programming Language :: Python :: 3
Classifier: Programming Language :: Python :: 3.4
Classifier: Programming Language :: Python :: 3.5
Classifier: Programming Language :: Python :: Implementation :: CPython
Requires-Dist: b3j0f.conf (>=0.3.19)
Requires-Dist: link.feature (>=2.1)
Requires-Dist: link.middleware (>=1.5)
